LICENSE.txt
MANIFEST.in
README.md
setup.py
Saltscaffold.egg-info/PKG-INFO
Saltscaffold.egg-info/SOURCES.txt
Saltscaffold.egg-info/dependency_links.txt
Saltscaffold.egg-info/entry_points.txt
Saltscaffold.egg-info/requires.txt
Saltscaffold.egg-info/top_level.txt
saltscaffold/MANIFEST.in
saltscaffold/__init__.py
saltscaffold/__init__.pyc
saltscaffold/__main__.py
saltscaffold/formulafiles.py
saltscaffold/formulafiles.pyc
saltscaffold/formulafolders.py
saltscaffold/formulafolders.pyc
saltscaffold/skel/.gitignore
saltscaffold/skel/.kitchen-ci.yml
saltscaffold/skel/.kitchen.yml
saltscaffold/skel/Gemfile
saltscaffold/skel/LICENSE.txt
saltscaffold/skel/README.md
saltscaffold/skel/pillar-custom.sls
saltscaffold/skel/formula/config.sls
saltscaffold/skel/formula/defaults.yml
saltscaffold/skel/formula/init.sls
saltscaffold/skel/formula/install.sls
saltscaffold/skel/formula/map.jinja
saltscaffold/skel/formula/service.sls
saltscaffold/skel/formula/files/config.conf
saltscaffold/skel/test/integration/default/serverspec/_spec.rb
saltscaffold/skel/test/mockup/init.sls