Metadata-Version: 1.0
Name: Saltscaffold
Version: 3.0.5
Summary: sets up files and directories for a new salt formula
Home-page: https://github.com/cmarzullo/saltsaffold
Author: Christopher Marzullo
Author-email: cmarzullo@linode.com
License: UNKNOWN
Platform: UNKNOWN
